{"name":"Driven","slug":"driven","version":"1.0.2","preview_url":"https://wp-themes.com/driven/","author":"themezee","screenshot_url":"//ts.w.org/wp-content/themes/driven/screenshot.png?ver=1.0.2","rating":100,"num_ratings":2,"homepage":"https://wordpress.org/themes/driven/","description":"Driven is a next generation block theme built for the new WordPress Full-Site-Editing experience. It comes with a clean and modern design and is packed with features, including a huge range of block patterns, multiple header and footer block template parts and support for global style variants."}